liams_simple_scaffold-0.1.8.data/scripts/make_scaffold.py
liams_simple_scaffold_pkg/__init__.py
liams_simple_scaffold_pkg/prefil/LICENSE_template
liams_simple_scaffold_pkg/prefil/MANIFEST_template.in
liams_simple_scaffold_pkg/prefil/README_template.md
liams_simple_scaffold_pkg/prefil/__init__.py
liams_simple_scaffold_pkg/prefil/gitignore_template
liams_simple_scaffold_pkg/prefil/main_template.py
liams_simple_scaffold_pkg/prefil/prefil_files.py
liams_simple_scaffold_pkg/prefil/setup_template.py
liams_simple_scaffold-0.1.8.dist-info/LICENSE
liams_simple_scaffold-0.1.8.dist-info/METADATA
liams_simple_scaffold-0.1.8.dist-info/WHEEL
liams_simple_scaffold-0.1.8.dist-info/top_level.txt
liams_simple_scaffold-0.1.8.dist-info/RECORD
