Metadata-Version: 2.1
Name: liams-simple-scaffold
Version: 0.1.8
Summary: A small scaffolding package
Home-page: https://github.com/shimbalama/liams_simple_scaffold.git
Author: Liam McIntyre
Author-email: shimbalama@gmail.com
License: UNKNOWN
Platform: UNKNOWN
Classifier: Programming Language :: Python :: 3
Classifier: License :: OSI Approved :: MIT License
Classifier: Operating System :: OS Independent
